LICENSE
MANIFEST.in
README.md
pyproject.toml
setup.cfg
src/discotime/__init__.py
src/discotime.egg-info/PKG-INFO
src/discotime.egg-info/SOURCES.txt
src/discotime.egg-info/dependency_links.txt
src/discotime.egg-info/requires.txt
src/discotime.egg-info/top_level.txt
src/discotime/datasets/__init__.py
src/discotime/datasets/from_rstats.py
src/discotime/datasets/utils.py
src/discotime/metrics/__init__.py
src/discotime/metrics/brier_score.py
src/discotime/models/__init__.py
src/discotime/models/components.py
src/discotime/models/models.py
src/discotime/utils/__init__.py
src/discotime/utils/estimators.py
src/discotime/utils/misc.py
src/discotime/utils/typing.py
tests/test_lightning_module.py
tests/test_metrics.py
tests/test_mgus2.py
tests/test_models.py
tests/test_preprocessing.py
tests/test_utils.py