Metadata-Version: 2.1
Name: discotime
Version: 0.0.4
Summary: Discrete-time competing risk analysis with neural networks
Home-page: https://github.com/peterchristofferholm/discotime
Author: Peter Holm
Author-email: "Peter Holm" <petchdk@gmail.com>
License: MIT
Classifier: License :: OSI Approved :: MIT License
Requires-Python: >=3.10
License-File: LICENSE
